{
  "id": "village-3",
  "biome": "village",
  "cols": 12,
  "rows": 18,
  "rows_data": [
    "............",
    ".B........B.",
    ".B..1AA2..B.",
    ".B..AYYA..B.",
    ".B..3AA4..B.",
    "............",
    "............",
    "............",
    "............",
    "............",
    "............",
    "............",
    "............",
    "............",
    "............",
    "............",
    "............",
    "............"
  ],
  "legend": {
    "1": "village_corner_tl",
    "2": "village_corner_tr",
    "3": "village_corner_bl",
    "4": "village_corner_br",
    "A": "village_basic",
    "B": "village_tough",
    "Y": "village_basic2"
  }
}
